elasticate-0.3.0.dist-info/METADATA
elasticate-0.3.0.dist-info/WHEEL
elasticate-0.3.0.dist-info/license_files/LICENSE
elasticate/stretch.py
elasticate/style.py
elasticate/layout.py
elasticate/__init__.py
elasticate/node.py
elasticate/elasticate.cpython-311-darwin.so
elasticate-0.3.0.dist-info/RECORD
