Metadata-Version: 2.1
Name: elasticate
Version: 0.3.0
Classifier: Development Status :: 4 - Beta
Classifier: Intended Audience :: Developers
Classifier: Programming Language :: Python :: 3
Classifier: Programming Language :: Rust
Classifier: Programming Language :: Python :: Implementation :: CPython
Classifier: Programming Language :: Python :: Implementation :: PyPy
Classifier: License :: OSI Approved :: MIT License
Classifier: Operating System :: OS Independent
Requires-Dist: maturin ==1.1.0 ; extra == 'build'
Requires-Dist: twine ; extra == 'build'
Provides-Extra: build
License-File: LICENSE
Summary: Python bindings for Stretch (high performance flexbox implementation)
Author: Kenneth Trelborg Vestergaard
Requires-Python: >=3.7
